faker_edu/__init__.py
faker_edu/tests/__init__.py
faker_edu/tests/test_faker_highered.py
faker_edu-1.1.0.dist-info/LICENSE
faker_edu-1.1.0.dist-info/METADATA
faker_edu-1.1.0.dist-info/WHEEL
faker_edu-1.1.0.dist-info/top_level.txt
faker_edu-1.1.0.dist-info/RECORD
