Metadata-Version: 2.1
Name: faker-edu
Version: 1.1.0
Summary: Provider for Faker which adds fake information about educational institutions and academics.
Home-page: https://github.com/SFDO-Community-Sprints/Snowfakery-Edu
Author: Allison Letts, Aaron Crosman, Paul Prescod
Classifier: Programming Language :: Python :: 3.8
Classifier: Programming Language :: Python :: 3.9
Classifier: Programming Language :: Python :: 3.10
Classifier: Programming Language :: Python :: 3.11
Classifier: Programming Language :: Python :: 3.12
Classifier: License :: OSI Approved :: BSD License
Classifier: Operating System :: OS Independent
License-File: LICENSE
Requires-Dist: faker
